recompi/__init__.py
recompi/recompi.py
recompi-2.0.20.dist-info/LICENSE
recompi-2.0.20.dist-info/METADATA
recompi-2.0.20.dist-info/WHEEL
recompi-2.0.20.dist-info/top_level.txt
recompi-2.0.20.dist-info/RECORD
