Metadata-Version: 2.1
Name: recompi
Version: 2.0.20
Summary: A Python wrapper for the RecomPI API
Author-email: RecomPI <tech@recompi.com>
Project-URL: Source, https://github.com/recompi/python-recompi
Project-URL: Use Cases, https://www.recompi.com/category/use-cases/documents-use-cases
Project-URL: Bug Tracker, https://github.com/recompi/python-recompi/issues
Project-URL: Website, https://www.recompi.com
Project-URL: Panel, https://panel.recompi.com
Project-URL: Wordpress Plugin, https://www.zhaket.com/web/recompi-plugin
Keywords: django,recompi,recommendation,tracking,recommender system,machine learning,data science,web development
Classifier: Development Status :: 5 - Production/Stable
Classifier: Programming Language :: Python :: 2
Classifier: Programming Language :: Python :: 3
Classifier: License :: OSI Approved :: MIT License
Classifier: Operating System :: OS Independent
Classifier: Intended Audience :: Developers
Classifier: License :: OSI Approved :: MIT License
Classifier: Operating System :: OS Independent
Classifier: Topic :: Software Development :: Libraries :: Python Modules
Requires-Python: >=2.7
License-File: LICENSE
Requires-Dist: requests >=2.25.1
